setup.cfg
setup.py
vcsecret/__init__.py
vcsecret/main.py
vcsecret/tests.py
vcsecret.egg-info/PKG-INFO
vcsecret.egg-info/SOURCES.txt
vcsecret.egg-info/dependency_links.txt
vcsecret.egg-info/entry_points.txt
vcsecret.egg-info/requires.txt
vcsecret.egg-info/top_level.txt