Metadata-Version: 1.1
Name: vcsecret
Version: 0.0.9
Summary: Keep your secrets in your VCS
Home-page: https://github.com/isra17/vcsecret
Author: isra17
Author-email: isra017@gmail.com
License: LGPL3
Keywords: secret config cryptography
Platform: UNKNOWN
Classifier: Development Status :: 3 - Alpha
Classifier: Intended Audience :: Developers
Classifier: License :: OSI Approved :: GNU Lesser General Public License v3 (LGPLv3)
Classifier: Programming Language :: Python :: 2.7
Classifier: Programming Language :: Python :: 3
Classifier: Topic :: Security :: Cryptography
Classifier: Topic :: Software Development :: Libraries
Classifier: Topic :: Utilities
